Metadata-Version: 2.1
Name: vielog
Version: 0.1
Summary: Logging wraper facility
Home-page: https://github.com/ftonioloviemar/vielog
Download-URL: https://github.com/ftonioloviemar/vielog/archive/refs/tags/v_0.1.tar.gz
Author: Fabio Toniolo Vieira Junior
Author-email: ftoniolo@viemar.com.br
License: MIT
Keywords: viemar,log
Classifier: Development Status :: 3 - Alpha
Classifier: Intended Audience :: Developers
Classifier: Topic :: Software Development :: Build Tools
Classifier: License :: OSI Approved :: MIT License
Classifier: Programming Language :: Python :: 3.6
Classifier: Programming Language :: Python :: 3.7
Classifier: Programming Language :: Python :: 3.8
Classifier: Programming Language :: Python :: 3.9
Classifier: Programming Language :: Python :: 3.10
Classifier: Programming Language :: Python :: 3.11
Classifier: Programming Language :: Python :: 3.12
License-File: LICENSE.txt
